setup.py
holdem/__init__.py
holdem/betting_rounds_holdem.py
holdem/dealer_holdem.py
holdem/deck.py
holdem/holdem_game.py
holdem/organize_pots.py
holdem/players.py
holdem/pokertable.py
holdem/rules_holdem.py
holdem/tests.py
poker_program_demo.egg-info/PKG-INFO
poker_program_demo.egg-info/SOURCES.txt
poker_program_demo.egg-info/dependency_links.txt
poker_program_demo.egg-info/entry_points.txt
poker_program_demo.egg-info/not-zip-safe
poker_program_demo.egg-info/top_level.txt