Metadata-Version: 1.0
Name: poker-program-demo
Version: 0.1.0
Summary: play poker; my first python project to learn
Home-page: https://bitbucket.org/codyc54321/poker_program_demo
Author: Cody Childers
Author-email: cchilder@mail.usf.edu
License: MIT
Platform: UNKNOWN
